{
  "kind": "youtube#playlist",
  "etag": "EhkMwKc5gjaGkuHFkS0kW7LYYgU",
  "id": "PLxlIzqc0aEwm4AlvW3PQaEkaoTmNy9FBW",
  "snippet": {
    "publishedAt": "2025-12-27T11:08:13.354319Z",
    "channelId": "UCmsKnHGCovc_WyXXBibVeBA",
    "title": "Agalloch",
    "description": "In my first year of college, I unplugged the earphones on my old Samsung laptop that had Linux Mint and lots of bugs instinctively, and the whole class ended up listening to Agalloch, screaming, shouting, and wailing. I hope my Electronics professor liked it.",
    "thumbnails": {
      "default": {
        "url": "https://i.ytimg.com/vi/fC0OFbhLeqk/default.jpg",
        "width": 120,
        "height": 90
      },
      "medium": {
        "url": "https://i.ytimg.com/vi/fC0OFbhLeqk/mqdefault.jpg",
        "width": 320,
        "height": 180
      },
      "high": {
        "url": "https://i.ytimg.com/vi/fC0OFbhLeqk/hqdefault.jpg",
        "width": 480,
        "height": 360
      },
      "standard": {
        "url": "https://i.ytimg.com/vi/fC0OFbhLeqk/sddefault.jpg",
        "width": 640,
        "height": 480
      },
      "maxres": {
        "url": "https://i.ytimg.com/vi/fC0OFbhLeqk/maxresdefault.jpg",
        "width": 1280,
        "height": 720
      }
    },
    "channelTitle": "zan",
    "localized": {
      "title": "Agalloch",
      "description": "In my first year of college, I unplugged the earphones on my old Samsung laptop that had Linux Mint and lots of bugs instinctively, and the whole class ended up listening to Agalloch, screaming, shouting, and wailing. I hope my Electronics professor liked it."
    }
  },
  "contentDetails": {
    "itemCount": 6
  },
  "playlist_items": {
    "kind": "youtube#playlistItemListResponse",
    "etag": "-M08K1kHWo1U5OVvPWdUo7iXwsw",
    "items": [
      {
        "kind": "youtube#playlistItem",
        "etag": "6ygv0Jee5bUwmkFVvn17zqiGLEQ",
        "id": "UEx4bEl6cWMwYUV3bTRBbHZXM1BRYUVrYW9UbU55OUZCVy4yODBDNjFEMDg1MDY2Mzc5",
        "snippet": {
          "publishedAt": "2025-12-27T11:08:13Z",
          "channelId": "UCmsKnHGCovc_WyXXBibVeBA",
          "title": "Limbs (2016 - Remaster)",
          "description": "Provided to YouTube by The End Records\n\nLimbs (2016 - Remaster) · Agalloch\n\nAshes Against The Grain\n\n℗ 2016 BMG Rights Management (US) LLC\n\nReleased on: 2016-07-15\n\nVocals, Producer: John Haughm\nProducer: Veleda Thorsson\nPiano, Producer, Sound  Engineer: Ronn Chick\nSound  Engineer: Colin Marston\nComposer: Anderson\nComposer: Greene\nComposer, Lyricist: Haughm\nComposer: J. William W.\n\nAuto-generated by YouTube.",
          "thumbnails": {
            "default": {
              "url": "https://i.ytimg.com/vi/fC0OFbhLeqk/default.jpg",
              "width": 120,
              "height": 90
            },
            "medium": {
              "url": "https://i.ytimg.com/vi/fC0OFbhLeqk/mqdefault.jpg",
              "width": 320,
              "height": 180
            },
            "high": {
              "url": "https://i.ytimg.com/vi/fC0OFbhLeqk/hqdefault.jpg",
              "width": 480,
              "height": 360
            },
            "standard": {
              "url": "https://i.ytimg.com/vi/fC0OFbhLeqk/sddefault.jpg",
              "width": 640,
              "height": 480
            },
            "maxres": {
              "url": "https://i.ytimg.com/vi/fC0OFbhLeqk/maxresdefault.jpg",
              "width": 1280,
              "height": 720
            }
          },
          "channelTitle": "zan",
          "playlistId": "PLxlIzqc0aEwm4AlvW3PQaEkaoTmNy9FBW",
          "position": 0,
          "resourceId": {
            "kind": "youtube#video",
            "videoId": "fC0OFbhLeqk"
          },
          "videoOwnerChannelTitle": "Agalloch - Topic",
          "videoOwnerChannelId": "UCO9bHbL-dJY1XUAq_yNicTw"
        }
      },
      {
        "kind": "youtube#playlistItem",
        "etag": "cMuUC0NbnLx_8H53b0mTciTw6rg",
        "id": "UEx4bEl6cWMwYUV3bTRBbHZXM1BRYUVrYW9UbU55OUZCVy41MkFEOUMzQ0I0NzY5Nzc5",
        "snippet": {
          "publishedAt": "2025-12-27T11:08:13Z",
          "channelId": "UCmsKnHGCovc_WyXXBibVeBA",
          "title": "This White Mountain On Which You Will Die (2016 - Remaster)",
          "description": "Provided to YouTube by The End Records\n\nThis White Mountain On Which You Will Die (2016 - Remaster) · Agalloch\n\nAshes Against The Grain\n\n℗ 2016 BMG Rights Management (US) LLC\n\nReleased on: 2016-07-15\n\nVocals, Producer: John Haughm\nProducer: Veleda Thorsson\nProducer, Sound  Engineer: Ronn Chick\nSound  Engineer: Colin Marston\nGuitar: Don Anderson\nComposer: Anderson\nComposer: Greene\nComposer, Lyricist: Haughm\nComposer: J. William W.\n\nAuto-generated by YouTube.",
          "thumbnails": {
            "default": {
              "url": "https://i.ytimg.com/vi/rTeOIpWR1Ic/default.jpg",
              "width": 120,
              "height": 90
            },
            "medium": {
              "url": "https://i.ytimg.com/vi/rTeOIpWR1Ic/mqdefault.jpg",
              "width": 320,
              "height": 180
            },
            "high": {
              "url": "https://i.ytimg.com/vi/rTeOIpWR1Ic/hqdefault.jpg",
              "width": 480,
              "height": 360
            },
            "standard": {
              "url": "https://i.ytimg.com/vi/rTeOIpWR1Ic/sddefault.jpg",
              "width": 640,
              "height": 480
            },
            "maxres": {
              "url": "https://i.ytimg.com/vi/rTeOIpWR1Ic/maxresdefault.jpg",
              "width": 1280,
              "height": 720
            }
          },
          "channelTitle": "zan",
          "playlistId": "PLxlIzqc0aEwm4AlvW3PQaEkaoTmNy9FBW",
          "position": 1,
          "resourceId": {
            "kind": "youtube#video",
            "videoId": "rTeOIpWR1Ic"
          },
          "videoOwnerChannelTitle": "Agalloch - Topic",
          "videoOwnerChannelId": "UCO9bHbL-dJY1XUAq_yNicTw"
        }
      },
      {
        "kind": "youtube#playlistItem",
        "etag": "sKwZOS9gROJgngh0upkAK1qmEXs",
        "id": "UEx4bEl6cWMwYUV3bTRBbHZXM1BRYUVrYW9UbU55OUZCVy4wNzJFMTA3NkMxMkQ5QjI0",
        "snippet": {
          "publishedAt": "2025-12-27T11:08:13Z",
          "channelId": "UCmsKnHGCovc_WyXXBibVeBA",
          "title": "Fire Above, Ice Below (2016 - Remaster)",
          "description": "Provided to YouTube by The End Records\n\nFire Above, Ice Below (2016 - Remaster) · Agalloch\n\nAshes Against The Grain\n\n℗ 2016 BMG Rights Management (US) LLC\n\nReleased on: 2016-07-15\n\nVocals, Producer: John Haughm\nProducer: Veleda Thorsson\nProducer, Sound  Engineer: Ronn Chick\nSound  Engineer: Colin Marston\nComposer: Anderson\nComposer: Greene\nComposer, Lyricist: Haughm\nComposer: J. William W.\n\nAuto-generated by YouTube.",
          "thumbnails": {
            "default": {
              "url": "https://i.ytimg.com/vi/2t1GE7RSw_k/default.jpg",
              "width": 120,
              "height": 90
            },
            "medium": {
              "url": "https://i.ytimg.com/vi/2t1GE7RSw_k/mqdefault.jpg",
              "width": 320,
              "height": 180
            },
            "high": {
              "url": "https://i.ytimg.com/vi/2t1GE7RSw_k/hqdefault.jpg",
              "width": 480,
              "height": 360
            },
            "standard": {
              "url": "https://i.ytimg.com/vi/2t1GE7RSw_k/sddefault.jpg",
              "width": 640,
              "height": 480
            },
            "maxres": {
              "url": "https://i.ytimg.com/vi/2t1GE7RSw_k/maxresdefault.jpg",
              "width": 1280,
              "height": 720
            }
          },
          "channelTitle": "zan",
          "playlistId": "PLxlIzqc0aEwm4AlvW3PQaEkaoTmNy9FBW",
          "position": 2,
          "resourceId": {
            "kind": "youtube#video",
            "videoId": "2t1GE7RSw_k"
          },
          "videoOwnerChannelTitle": "Agalloch - Topic",
          "videoOwnerChannelId": "UCO9bHbL-dJY1XUAq_yNicTw"
        }
      },
      {
        "kind": "youtube#playlistItem",
        "etag": "BV8pdRqLwUNREPvadVKlDYsAa7I",
        "id": "UEx4bEl6cWMwYUV3bTRBbHZXM1BRYUVrYW9UbU55OUZCVy4wRTQxMjVCMDExRDRDNkM5",
        "snippet": {
          "publishedAt": "2025-12-27T11:08:13Z",
          "channelId": "UCmsKnHGCovc_WyXXBibVeBA",
          "title": "Not Unlike The Waves (2016 - Remaster)",
          "description": "Provided to YouTube by The End Records\n\nNot Unlike The Waves (2016 - Remaster) · Agalloch\n\nAshes Against The Grain\n\n℗ 2016 BMG Rights Management (US) LLC\n\nReleased on: 2016-07-15\n\nVocals, Producer: John Haughm\nProducer: Veleda Thorsson\nProducer, Sound  Engineer: Ronn Chick\nSound  Engineer: Colin Marston\nGuitar: Don Anderson\nComposer: Anderson\nComposer: Greene\nComposer, Lyricist: Haughm\nComposer: J. William W.\n\nAuto-generated by YouTube.",
          "thumbnails": {
            "default": {
              "url": "https://i.ytimg.com/vi/gDH-YCCeL3c/default.jpg",
              "width": 120,
              "height": 90
            },
            "medium": {
              "url": "https://i.ytimg.com/vi/gDH-YCCeL3c/mqdefault.jpg",
              "width": 320,
              "height": 180
            },
            "high": {
              "url": "https://i.ytimg.com/vi/gDH-YCCeL3c/hqdefault.jpg",
              "width": 480,
              "height": 360
            },
            "standard": {
              "url": "https://i.ytimg.com/vi/gDH-YCCeL3c/sddefault.jpg",
              "width": 640,
              "height": 480
            },
            "maxres": {
              "url": "https://i.ytimg.com/vi/gDH-YCCeL3c/maxresdefault.jpg",
              "width": 1280,
              "height": 720
            }
          },
          "channelTitle": "zan",
          "playlistId": "PLxlIzqc0aEwm4AlvW3PQaEkaoTmNy9FBW",
          "position": 3,
          "resourceId": {
            "kind": "youtube#video",
            "videoId": "gDH-YCCeL3c"
          },
          "videoOwnerChannelTitle": "Agalloch - Topic",
          "videoOwnerChannelId": "UCO9bHbL-dJY1XUAq_yNicTw"
        }
      },
      {
        "kind": "youtube#playlistItem",
        "etag": "O2nz3fX9OXV2CTMFETelSPLmJTk",
        "id": "UEx4bEl6cWMwYUV3bTRBbHZXM1BRYUVrYW9UbU55OUZCVy42MzJCQTFEOEFFRkVGM0M0",
        "snippet": {
          "publishedAt": "2025-12-27T11:08:13Z",
          "channelId": "UCmsKnHGCovc_WyXXBibVeBA",
          "title": "Our Fortress Is Burning... I (2016 - Remaster)",
          "description": "Provided to YouTube by The End Records\n\nOur Fortress Is Burning... I (2016 - Remaster) · Agalloch\n\nAshes Against The Grain\n\n℗ 2016 BMG Rights Management (US) LLC\n\nReleased on: 2016-07-15\n\nVocals, Producer: John Haughm\nProducer: Veleda Thorsson\nPiano, Producer, Sound  Engineer: Ronn Chick\nSound  Engineer: Colin Marston\nGuitar: Don Anderson\nComposer: Anderson\nComposer: Greene\nComposer, Lyricist: Haughm\nComposer: J. William W.\n\nAuto-generated by YouTube.",
          "thumbnails": {
            "default": {
              "url": "https://i.ytimg.com/vi/Jert-Hg3pzs/default.jpg",
              "width": 120,
              "height": 90
            },
            "medium": {
              "url": "https://i.ytimg.com/vi/Jert-Hg3pzs/mqdefault.jpg",
              "width": 320,
              "height": 180
            },
            "high": {
              "url": "https://i.ytimg.com/vi/Jert-Hg3pzs/hqdefault.jpg",
              "width": 480,
              "height": 360
            },
            "standard": {
              "url": "https://i.ytimg.com/vi/Jert-Hg3pzs/sddefault.jpg",
              "width": 640,
              "height": 480
            },
            "maxres": {
              "url": "https://i.ytimg.com/vi/Jert-Hg3pzs/maxresdefault.jpg",
              "width": 1280,
              "height": 720
            }
          },
          "channelTitle": "zan",
          "playlistId": "PLxlIzqc0aEwm4AlvW3PQaEkaoTmNy9FBW",
          "position": 4,
          "resourceId": {
            "kind": "youtube#video",
            "videoId": "Jert-Hg3pzs"
          },
          "videoOwnerChannelTitle": "Agalloch - Topic",
          "videoOwnerChannelId": "UCO9bHbL-dJY1XUAq_yNicTw"
        }
      },
      {
        "kind": "youtube#playlistItem",
        "etag": "-W79VoN8vBH6hj3VpGFMk-GAKa4",
        "id": "UEx4bEl6cWMwYUV3bTRBbHZXM1BRYUVrYW9UbU55OUZCVy45QUZDNTQyMjg2REJDQUM0",
        "snippet": {
          "publishedAt": "2025-12-27T11:08:13Z",
          "channelId": "UCmsKnHGCovc_WyXXBibVeBA",
          "title": "Our Fortress Is Burning... II - Bloodbirds (2016 - Remaster)",
          "description": "Provided to YouTube by The End Records\n\nOur Fortress Is Burning... II - Bloodbirds (2016 - Remaster) · Agalloch\n\nAshes Against The Grain\n\n℗ 2016 BMG Rights Management (US) LLC\n\nReleased on: 2016-07-15\n\nVocals, Producer: John Haughm\nProducer: Veleda Thorsson\nProducer, Sound  Engineer: Ronn Chick\nSound  Engineer: Colin Marston\nGuitar: Don Anderson\nComposer: Anderson\nComposer: Greene\nComposer, Lyricist: Haughm\nComposer: J. William W.\n\nAuto-generated by YouTube.",
          "thumbnails": {
            "default": {
              "url": "https://i.ytimg.com/vi/ikPNLmhHs0o/default.jpg",
              "width": 120,
              "height": 90
            },
            "medium": {
              "url": "https://i.ytimg.com/vi/ikPNLmhHs0o/mqdefault.jpg",
              "width": 320,
              "height": 180
            },
            "high": {
              "url": "https://i.ytimg.com/vi/ikPNLmhHs0o/hqdefault.jpg",
              "width": 480,
              "height": 360
            },
            "standard": {
              "url": "https://i.ytimg.com/vi/ikPNLmhHs0o/sddefault.jpg",
              "width": 640,
              "height": 480
            },
            "maxres": {
              "url": "https://i.ytimg.com/vi/ikPNLmhHs0o/maxresdefault.jpg",
              "width": 1280,
              "height": 720
            }
          },
          "channelTitle": "zan",
          "playlistId": "PLxlIzqc0aEwm4AlvW3PQaEkaoTmNy9FBW",
          "position": 5,
          "resourceId": {
            "kind": "youtube#video",
            "videoId": "ikPNLmhHs0o"
          },
          "videoOwnerChannelTitle": "Agalloch - Topic",
          "videoOwnerChannelId": "UCO9bHbL-dJY1XUAq_yNicTw"
        }
      }
    ],
    "pageInfo": {
      "totalResults": 6,
      "resultsPerPage": 50
    }
  }
}